.travis.yml
LICENSE
MANIFEST.in
README.rst
setup.cfg
setup.py
tox.ini
Mopidy_PlayerFM.egg-info/PKG-INFO
Mopidy_PlayerFM.egg-info/SOURCES.txt
Mopidy_PlayerFM.egg-info/dependency_links.txt
Mopidy_PlayerFM.egg-info/entry_points.txt
Mopidy_PlayerFM.egg-info/not-zip-safe
Mopidy_PlayerFM.egg-info/requires.txt
Mopidy_PlayerFM.egg-info/top_level.txt
mopidy_playerfm/__init__.py
mopidy_playerfm/backend.py
mopidy_playerfm/ext.conf
mopidy_playerfm/library.py
mopidy_playerfm/playback.py
mopidy_playerfm/playlists.py
mopidy_playerfm/repeating_timer.py
mopidy_playerfm/session.py
tests/__init__.py
tests/test_extension.py