Metadata-Version: 1.1
Name: Mopidy-PlayerFM
Version: 0.1.0
Summary: Mopidy extension for PlayerFM
Home-page: https://github.com/ohporter/mopidy-playerfm
Author: Matt Porter
Author-email: mporter@konsulko.com
License: Apache License, Version 2.0
Platform: UNKNOWN
Classifier: Environment :: No Input/Output (Daemon)
Classifier: Intended Audience :: End Users/Desktop
Classifier: License :: OSI Approved :: Apache Software License
Classifier: Operating System :: OS Independent
Classifier: Programming Language :: Python :: 2
Classifier: Topic :: Multimedia :: Sound/Audio :: Players
